adomo/__init__.py
adomo/api_client.py
adomo/api_response.py
adomo/configuration.py
adomo/exceptions.py
adomo/py.typed
adomo/rest.py
adomo/api/__init__.py
adomo/api/activities_api.py
adomo/api/ai_api.py
adomo/api/api_service_api.py
adomo/api/auth_api.py
adomo/api/graphql_api.py
adomo/api/integrations_api.py
adomo/api/jobs_api.py
adomo/api/schedules_api.py
adomo/api/users_api.py
adomo/api/workflows_api.py
adomo/models/__init__.py
adomo/models/activity_input.py
adomo/models/activity_invocation_input.py
adomo/models/activity_invocation_output.py
adomo/models/activity_output.py
adomo/models/activity_state.py
adomo/models/activity_statement_input.py
adomo/models/activity_statement_output.py
adomo/models/agent_config_input.py
adomo/models/agent_config_input_mcp_servers_value.py
adomo/models/agent_config_output.py
adomo/models/attribute.py
adomo/models/backfill_request.py
adomo/models/child_workflow_invocation_input.py
adomo/models/child_workflow_invocation_output.py
adomo/models/child_workflow_statement_input.py
adomo/models/child_workflow_statement_output.py
adomo/models/command.py
adomo/models/condition_invocation_input.py
adomo/models/condition_invocation_output.py
adomo/models/condition_statement_input.py
adomo/models/condition_statement_output.py
adomo/models/create_schedule_request.py
adomo/models/cwd.py
adomo/models/dependency.py
adomo/models/dsl.py
adomo/models/execution_status.py
adomo/models/field_type.py
adomo/models/group.py
adomo/models/health_response.py
adomo/models/health_status.py
adomo/models/history_event_response.py
adomo/models/http_validation_error.py
adomo/models/job_response.py
adomo/models/jobs_response.py
adomo/models/jobs_sort_on.py
adomo/models/json_value.py
adomo/models/mcp_image_config.py
adomo/models/mcp_sse_config.py
adomo/models/mcp_stdio_config.py
adomo/models/model_field.py
adomo/models/model_schema.py
adomo/models/output_format.py
adomo/models/output_format_type.py
adomo/models/page_info.py
adomo/models/page_size.py
adomo-1.1.0.dist-info/METADATA
adomo-1.1.0.dist-info/WHEEL
adomo-1.1.0.dist-info/top_level.txt
adomo-1.1.0.dist-info/RECORD
