Metadata-Version: 2.4
Name: adomo
Version: 1.1.0
Summary: CxO Bot Automation API
Home-page: https://github.com/CxOAGI/cxobot
Author: OpenAPI Generator community
Author-email: OpenAPI Generator Community <team@openapitools.org>
Project-URL: Repository, https://github.com/CxOAGI/cxobot
Keywords: OpenAPI,OpenAPI-Generator,CxO Bot Automation API
Requires-Python: >=3.9
Requires-Dist: urllib3<3.0.0,>=2.1.0
Requires-Dist: python-dateutil>=2.8.2
Requires-Dist: pydantic>=2
Requires-Dist: typing-extensions>=4.7.1
Requires-Dist: lazy-imports<2,>=1
Dynamic: author
Dynamic: home-page
